farnsworth/__init__.py
farnsworth/client.py
farnsworth/agents/__init__.py
farnsworth/agents/agent_debates.py
farnsworth/agents/base_agent.py
farnsworth/agents/critic_agent.py
farnsworth/agents/filesystem_agent.py
farnsworth/agents/hierarchical_teams.py
farnsworth/agents/meta_cognition.py
farnsworth/agents/planner_agent.py
farnsworth/agents/proactive_agent.py
farnsworth/agents/specialist_agents.py
farnsworth/agents/specialization_learning.py
farnsworth/agents/swarm_orchestrator.py
farnsworth/agents/user_avatar.py
farnsworth/agents/web_agent.py
farnsworth/collaboration/__init__.py
farnsworth/collaboration/multi_user.py
farnsworth/collaboration/permissions.py
farnsworth/collaboration/sessions.py
farnsworth/collaboration/shared_memory.py
farnsworth/core/__init__.py
farnsworth/core/inference_engine.py
farnsworth/core/llm_backend.py
farnsworth/core/model_manager.py
farnsworth/core/model_swarm.py
farnsworth/core/resilience.py
farnsworth/evolution/__init__.py
farnsworth/evolution/behavior_mutation.py
farnsworth/evolution/fitness_tracker.py
farnsworth/evolution/genetic_optimizer.py
farnsworth/evolution/lora_evolver.py
farnsworth/integration/__init__.py
farnsworth/integration/multimodal.py
farnsworth/integration/tool_router.py
farnsworth/integration/video.py
farnsworth/integration/vision.py
farnsworth/integration/voice.py
farnsworth/mcp_server/__init__.py
farnsworth/mcp_server/agent_tools.py
farnsworth/mcp_server/evolution_tools.py
farnsworth/mcp_server/memory_tools.py
farnsworth/mcp_server/resources.py
farnsworth/mcp_server/server.py
farnsworth/memory/__init__.py
farnsworth/memory/archival_memory.py
farnsworth/memory/episodic_memory.py
farnsworth/memory/knowledge_graph.py
farnsworth/memory/knowledge_graph_v2.py
farnsworth/memory/memory_dreaming.py
farnsworth/memory/memory_sharing.py
farnsworth/memory/memory_system.py
farnsworth/memory/recall_memory.py
farnsworth/memory/semantic_layers.py
farnsworth/memory/sharding.py
farnsworth/memory/virtual_context.py
farnsworth_ai-1.0.0.dist-info/licenses/LICENSE
farnsworth_ai-1.0.0.dist-info/METADATA
farnsworth_ai-1.0.0.dist-info/WHEEL
farnsworth_ai-1.0.0.dist-info/entry_points.txt
farnsworth_ai-1.0.0.dist-info/top_level.txt
farnsworth_ai-1.0.0.dist-info/RECORD
