Metadata-Version: 2.4
Name: farnsworth-ai
Version: 1.0.0
Summary: Self-evolving companion AI with MemGPT-style memory and LangGraph agent swarm
Author: Farnsworth Team
License: MIT
Keywords: ai,llm,memory,agents,evolution,mcp
Classifier: Development Status :: 3 - Alpha
Classifier: Intended Audience :: Developers
Classifier: License :: OSI Approved :: MIT License
Classifier: Programming Language :: Python :: 3.10
Classifier: Programming Language :: Python :: 3.11
Classifier: Programming Language :: Python :: 3.12
Requires-Python: >=3.10
License-File: LICENSE
Requires-Dist: ollama>=0.4.0
Requires-Dist: llama-cpp-python>=0.3.0
Requires-Dist: faiss-cpu>=1.8.0
Requires-Dist: chromadb>=0.5.0
Requires-Dist: sentence-transformers>=3.0.0
Requires-Dist: networkx>=3.0
Requires-Dist: langgraph>=0.2.0
Requires-Dist: langchain>=0.3.0
Requires-Dist: langchain-community>=0.3.0
Requires-Dist: llama-index>=0.11.0
Requires-Dist: rank-bm25>=0.2.0
Requires-Dist: deap>=1.4.0
Requires-Dist: stable-baselines3>=2.3.0
Requires-Dist: peft>=0.13.0
Requires-Dist: mcp>=1.0.0
Requires-Dist: streamlit>=1.38.0
Requires-Dist: pyyaml>=6.0
Requires-Dist: loguru>=0.7.0
Requires-Dist: numpy>=1.24.0
Requires-Dist: pydantic>=2.0.0
Requires-Dist: aiohttp>=3.9.0
Requires-Dist: httpx>=0.27.0
Requires-Dist: opencv-python-headless>=4.8.0
Requires-Dist: pillow>=10.0.0
Provides-Extra: dev
Requires-Dist: pytest>=8.0.0; extra == "dev"
Requires-Dist: pytest-asyncio>=0.23.0; extra == "dev"
Requires-Dist: pytest-cov>=4.0.0; extra == "dev"
Requires-Dist: black>=24.0.0; extra == "dev"
Requires-Dist: ruff>=0.3.0; extra == "dev"
Requires-Dist: mypy>=1.8.0; extra == "dev"
Provides-Extra: gpu
Requires-Dist: faiss-gpu>=1.8.0; extra == "gpu"
Requires-Dist: torch>=2.0.0; extra == "gpu"
Dynamic: license-file
